dmt/__init__.py
dmt/constants.py
dmt/data/__init__.py
dmt/data/image_base.py
dmt/data/images.py
dmt/data/label_base.py
dmt/data/label_categories.py
dmt/data/label_masks.py
dmt/data/loading/__init__.py
dmt/data/loading/collate.py
dmt/data/loading/mtm_loader.py
dmt/data/loading/otm_loader.py
dmt/data/loading/oto_loader.py
dmt/data/loading/patches/__init__.py
dmt/data/loading/patches/samplers_base.py
dmt/data/loading/patches/uniform.py
dmt/data/samples/__init__.py
dmt/data/samples/sample.py
dmt/data/samples/sampleset.py
dmt/losses/__init__.py
dmt/losses/classification.py
dmt/losses/contrastive.py
dmt/losses/losses3d.py
dmt/losses/segmentation.py
dmt/metrics/__init__.py
dmt/metrics/classification.py
dmt/metrics/medpy_metrics.py
dmt/metrics/segmentation3d.py
dmt/nets/__init__.py
dmt/nets/base_model.py
dmt/nets/densenet.py
dmt/nets/efficientnet.py
dmt/nets/resnet.py
dmt/nets/unets/__init__.py
dmt/nets/unets/bigunet2d.py
dmt/nets/unets/denseunet2d.py
dmt/nets/unets/unet2d.py
dmt/nets/unets/unet3d.py
dmt/transforms/__init__.py
dmt/transforms/harmonizer.py
dmt/transforms/transform_base.py
dmt/utils/__init__.py
dmt/utils/devices.py
dmt/utils/parallel.py
dmt/utils/parse.py
dmt/utils/queues.py
dmt/utils/timers.py
dmt/utils/images/__init__.py
dmt/utils/images/np_image.py
dmt/utils/images/sitk_image.py
dmt/utils/images/visualize.py
dmt/utils/io/__init__.py
dmt/utils/io/files.py
dmt/utils/io/images2d.py
dmt/utils/io/images3d.py
dmt/utils/io/output.py
dmt/utils/train/__init__.py
dmt/utils/train/ramps.py
dmt/utils/train/schedulers.py
dmt/utils/train/statistics.py
deep_medical_toolkit-0.0.4.dist-info/LICENSE
deep_medical_toolkit-0.0.4.dist-info/METADATA
deep_medical_toolkit-0.0.4.dist-info/WHEEL
deep_medical_toolkit-0.0.4.dist-info/top_level.txt
deep_medical_toolkit-0.0.4.dist-info/RECORD
