Metadata-Version: 2.1
Name: deep-medical-toolkit
Version: 0.0.4
Summary: Tools to facilitate deep learning research with a focus on medical imaging.
Home-page: UNKNOWN
Author: Charley Zhang
Author-email: yzhang46@nd.edu
License: Apache License 2.0
Keywords: dmt
Platform: UNKNOWN
Classifier: Natural Language :: English
Classifier: Programming Language :: Python :: 3
Classifier: Programming Language :: Python :: 3.9
Requires-Dist: SimpleITK (!=2.0.*)
Requires-Dist: nibabel
Requires-Dist: numpy (>=1.15)
Requires-Dist: scipy
Requires-Dist: scikit-image
Requires-Dist: Pillow
Requires-Dist: torch (>=1.1)
Requires-Dist: torchvision
Requires-Dist: torch-summary
Requires-Dist: pandas
Requires-Dist: psutil
Requires-Dist: matplotlib
Requires-Dist: wandb
Requires-Dist: tqdm
